{"# of languages: {0}": "Anzahl der Sprachen: {0}", "(current)": "(Aktuell)", "(no exact match)": "(Keine genaue \u00dcbereinstimmung)", "(none)": "(None)", "(not found)": "(Nicht gefunden)", "(not set)": "(Nicht festgelegt)", "AM/PM Strings": "AM / PM Strings", "Additional relevant standards": "Weitere relevante Normen", "All": "Alle", "All your base are belong to us": "Alle Ihre Basis sind geh\u00f6ren zu uns", "Arguments": "Argumente", "Base locale ID": "Base Gebietsschema-ID", "Basic Information": "Grundlegende Informationen", "Change Language": "Sprache \u00e4ndern", "Change language": "Sprache \u00e4ndern", "Character orientation": "Charakter-Orientierung", "Children:": "Kinder:", "Compare Currency Patterns": "Vergleichen W\u00e4hrung Patterns", "Compare Date Patterns": "Vergleichen Datum Patterns", "Compare Locale Data Sources": "Vergleichen Locale Data Sources", "Compare Time Patterns": "Vergleichen Zeitmuster", "Compare again": "Vergleichen Sie wieder", "Compare two data sources and see which locales that are in one but not the other.": "Vergleichen Sie zwei Datenquellen und welche Sprachen, die in einem sind aber nicht die anderen.", "Compare:": "Vergleichen mit:", "Complete List": "Komplette Liste", "Contact": "Kontakt", "Continue": "Weiter", "Countries": "L\u00e4nder", "Countries with language {0} ({1})": "L\u00e4nder mit Sprache {0} ({1})", "Country": "Land", "Currency symbol": "W\u00e4hrungssymbol", "Data": "Daten", "Data Source Comparison for {0}": "Data Source Vergleich f\u00fcr {0}", "Data source": "Quelle der Daten", "Date Order": "Datum Auftrag", "Date Pattern": "Datum Muster", "Dates": "Termine", "Decimal Symbols": "Dezimalzeichen", "Decimal separator": "Dezimaltrennzeichen", "Decimal\u00a0Digits": "Dezimal? Digits", "Decimal\u00a0Separator": "Dezimal? Separator", "Description": "Beschreibung", "Digit": "Stelligen", "Display Name": "Angezeigter Name", "Display name": "Anzeigename", "Display name with dialect": "Anzeigename mit Dialekt", "Display variant": "Display-Variante", "E.T. phone home": "E.T. nach Hause telefonieren", "Email:": "E-Mail:", "English": "Englisch", "Era names": "\u00c4ranamen", "Examples": "Beispiele", "Exponent separator": "Exponent Separator", "Extended Locales": "Erweiterte Sprachumgebungen", "File name": "Dateiname", "File\u00a0name": "Datei? Name", "Function": "Funktion", "General Information": "Allgemeine Informationen", "Google Translate Language \u201c{0}\u201d": "Google Translate Sprache? {0}?", "Google Translate Languages": "Google Translate Sprachen", "Grand total: {0}": "Gesamtsumme: {0}", "Grouping separator": "Gruppierung Separator", "Grouping\u00a0Separator": "Gruppierung? Separator", "Hello world!": "Hallo Welt!", "Help me!": "Helfen Sie mir!", "Home": "Nach Hause", "Houston, we have a problem": "Houston, wir haben ein Problem", "ICU locales in this country": "ICU locales in diesem Land", "ICU locales using this language": "ICU locales mit dieser Sprache", "ISO 3166 Country List": "ISO 3166 L\u00e4nderliste", "In both": "In beiden", "In dreams you can see yourself without using mirrors": "Im Traum kann man sich ohne Hilfe von Spiegeln sehen", "International Components for Unicode ({0}ICU{1}) Data": "International Components for Unicode (ICU {0} {1}) Data", "International currency symbol": "Internationales W\u00e4hrungssymbol", "Java Locale \u201c{0}\u201d ({1})": "Java Gebietsschema? {0}? ({1})", "Java Locales": "Java-Sprachumgebungen", "Keep off the grass": "Betreten des Rasens", "Language": "Sprache", "Languages": "Sprachen", "Languages with Countries": "Sprachen mit den L\u00e4ndern", "Library": "Bibliothek", "Line orientation": "Line Orientierung", "Lists:": "Listen:", "Local Name": "Lokaler Name", "Local name": "Lokaler Name", "Locale": "Ort", "LocalePlanet: L10N and I18N for JavaScript": "LocalePlanet: L10N und I18N f\u00fcr JavaScript", "Locales to check:": "Locales zu \u00fcberpr\u00fcfen:", "Localization and Internationalization for JavaScript": "Lokalisierung und Internationalisierung f\u00fcr JavaScript", "Long Names": "Lange Namen", "Long/Daylight": "Long / Daylight", "Long/Standard": "Long / Standard", "Message": "Nachricht", "Message:": "Nachricht:", "Microsoft .NET CultureInfo \u201c{0}\u201d ({1})": "Microsoft. NET CultureInfo? {0}? ({1})", "Minus sign": "Minus", "Minus\u00a0Sign": "Minus? Anmelden", "Missing": "Fehlende", "Missing Locales": "Fehlende Sprachumgebungen", "Monetary decimal separator": "Monet\u00e4re Dezimaltrennzeichen", "Months": "Monate", "Name in data source": "Name in der Datenquelle", "No": "Nein", "No, you're not coming!": "Nein, du bist nicht kommen!", "Non-Google name": "Nicht-Google-Namen", "Now ({0})": "Jetzt ({0})", "Numbers": "Zahlen", "Obsolete:": "Veraltet:", "Only in {0}": "Nur in {0}", "Options": "Optionen", "Options:": "Optionen:", "Other data sources": "Andere Datenquellen", "Output": "Ausgang", "Overview": "\u00dcbersicht", "Pad escape": "Pad Flucht", "Pattern": "Muster", "Pattern Separator": "Muster Separator", "Per mill": "Promille", "Percent": "Prozent", "Please may I have some lemons?": "Bitte kann ich einige Zitronen?", "Plus sign": "Pluszeichen", "Property": "Immobilien", "Put your hands where I can see them!": "Legen Sie Ihre H\u00e4nde, wo ich sie sehen kann!", "Related ICU Locales": "Verwandte ICU-Sprachumgebungen", "Result": "Ergebnis", "Rounding": "Runden", "Sample": "H\u00f6rbeispiel", "Sample Translations": "Probe\u00fcbersetzungen", "Select": "W\u00e4hlen Sie", "Short Names": "Kurznamen", "Short months": "Kurzen Monaten", "Short weekdays": "Kurze Woche", "Short/Daylight": "Kurze / Daylight", "Short/Standard": "Kurze / Standard", "Show locales in common": "Show locales gemeinsam", "Siblings:": "Geschwister:", "Significant digit": "Signifikante Ziffern", "Simple (xx-XX) Locales": "Simple (xx-XX) Gebietsschemas", "Supported Languages": "Unterst\u00fctzte Sprachen", "Supported?": "Unterst\u00fctzt?", "Talk is cheap. Show me the code.": "Reden ist billig. Zeigen Sie mir den Code.", "Thanks for your feedback!": "Vielen Dank f\u00fcr Ihr Feedback!", "There's no place like home": "Es gibt keinen Ort wie zu Hause", "This is the list of ISO 3166 countries via <code>ULocale.getISOCountries()</code>.": "Dies ist die Liste der ISO 3166 \u00fcber L\u00e4nder <code>ULocale.getISOCountries()</code> .", "This is the list of ISO 639 languages via <code>ULocale.getISOLanguages()</code>.": "Dies ist die Liste von ISO 639 Sprachen \u00fcber <code>ULocale.getISOLanguages()</code> .", "This sitemap is meant for robots, not humans, but feel free to browse anyway! Or try the {0}raw XML view{1}.": "Diese Sitemap ist f\u00fcr Roboter, keine Menschen gemeint, aber z\u00f6gern Sie trotzdem! Oder probieren Sie die {0} rohen XML-Ansicht {1}.", "Time Zones": "Zeitzonen", "Today": "Heute", "Today is {0}": "Heute ist der {0}", "Total:": "Gesamt:", "Toto, I've a feeling we're not in Kansas anymore": "Toto, ich habe das Gef\u00fchl, wir sind nicht mehr in Kansas", "Translatable?": "\u00dcbersetzbar?", "Usage": "Nutzung", "Value": "Preis", "Value(s)": "Wert (e)", "Visitor Locale Statistics": "Besucher Locale Statistik", "Weekdays": "Wochentags", "What we've got here is failure to communicate": "Was wir hier haben ist das Versagen der Kommunikation", "Yes": "Ja", "You have {0} lives remaining": "Sie haben {0} lebt noch", "You must pick two different data sources to compare": "Sie m\u00fcssen w\u00e4hlen Sie zwei unterschiedliche Datenquellen zu vergleichen", "Your query matched {0} files in {1} directories.": "Ihre Anfrage abgestimmt {0} Dateien in {1} Verzeichnisse.", "Zero digit": "Zero stelligen", "all": "alle", "compare": "vergleichen", "compare two data sources to see which locales are missing.": "Vergleich von zwei Datenquellen, um zu sehen, welche Sprachen fehlen.", "complex locales": "Komplex locales", "currency patterns": "W\u00e4hrung Muster", "date patterns": "Datum Muster", "languages": "Sprachen", "not a SimpleDateFormat": "kein SimpleDateFormat", "simple locales": "einfache locales", "time patterns": "Zeitmuster", "unknown": "unbekannt", "{0}Google Translate{1} Languages": "{0} Google Translate {1} Sprachen", "{0}Java{1} Locales": "{0} {1} Java-Sprachumgebungen"}